README.rst
setup.py
audiogen/__init__.py
audiogen/filters.py
audiogen/generators.py
audiogen/noise.py
audiogen/sampler.py
audiogen/util.py
audiogen.egg-info/PKG-INFO
audiogen.egg-info/SOURCES.txt
audiogen.egg-info/dependency_links.txt
audiogen.egg-info/requires.txt
audiogen.egg-info/top_level.txt
test/test.py