Metadata-Version: 1.1
Name: audiogen
Version: 0.1.2
Summary: Generator based tools for working with audio clips.
Home-page: https://github.com/casebeer/audiogen
Author: Christopher H. Casebeer
Author-email: UNKNOWN
License: UNKNOWN
Platform: UNKNOWN
Classifier: License :: OSI Approved :: BSD License
Classifier: Programming Language :: Python :: 2.6
Classifier: Programming Language :: Python :: 2.7
Classifier: Intended Audience :: Developers
Classifier: Topic :: Multimedia :: Sound/Audio
